interactive_sdk/__init__.py
interactive_sdk/client/__init__.py
interactive_sdk/client/driver.py
interactive_sdk/client/result.py
interactive_sdk/client/session.py
interactive_sdk/client/status.py
interactive_sdk/openapi/__init__.py
interactive_sdk/openapi/api_client.py
interactive_sdk/openapi/api_response.py
interactive_sdk/openapi/configuration.py
interactive_sdk/openapi/exceptions.py
interactive_sdk/openapi/rest.py
interactive_sdk/openapi/api/__init__.py
interactive_sdk/openapi/api/admin_service_graph_management_api.py
interactive_sdk/openapi/api/admin_service_job_management_api.py
interactive_sdk/openapi/api/admin_service_procedure_management_api.py
interactive_sdk/openapi/api/admin_service_service_management_api.py
interactive_sdk/openapi/api/graph_service_edge_management_api.py
interactive_sdk/openapi/api/graph_service_vertex_management_api.py
interactive_sdk/openapi/api/query_service_api.py
interactive_sdk/openapi/models/__init__.py
interactive_sdk/openapi/models/base_edge_type.py
interactive_sdk/openapi/models/base_edge_type_vertex_type_pair_relations_inner.py
interactive_sdk/openapi/models/base_edge_type_vertex_type_pair_relations_inner_x_csr_params.py
interactive_sdk/openapi/models/base_property_meta.py
interactive_sdk/openapi/models/base_vertex_type.py
interactive_sdk/openapi/models/base_vertex_type_x_csr_params.py
interactive_sdk/openapi/models/collection.py
interactive_sdk/openapi/models/collective_results.py
interactive_sdk/openapi/models/column.py
interactive_sdk/openapi/models/column_mapping.py
interactive_sdk/openapi/models/create_edge_type.py
interactive_sdk/openapi/models/create_graph_request.py
interactive_sdk/openapi/models/create_graph_response.py
interactive_sdk/openapi/models/create_graph_schema_request.py
interactive_sdk/openapi/models/create_procedure_request.py
interactive_sdk/openapi/models/create_procedure_response.py
interactive_sdk/openapi/models/create_property_meta.py
interactive_sdk/openapi/models/create_vertex_type.py
interactive_sdk-0.0.3.dist-info/METADATA
interactive_sdk-0.0.3.dist-info/WHEEL
interactive_sdk-0.0.3.dist-info/top_level.txt
interactive_sdk-0.0.3.dist-info/RECORD
