Metadata-Version: 2.1
Name: interactive-sdk
Version: 0.0.3
Summary: GraphScope Interactive API v0.0.3
Home-page: 
Author: OpenAPI Generator community
Author-email: graphscope@alibaba-inc.com
License: Apache 2.0
Keywords: OpenAPI,OpenAPI-Generator,GraphScope Interactive API v0.0.3
Requires-Dist: urllib3 (<2.1.0,>=1.25.3)
Requires-Dist: python-dateutil
Requires-Dist: pydantic (>=2)
Requires-Dist: typing-extensions (>=4.7.1)
Requires-Dist: neo4j (>=4.4.19)
Requires-Dist: gremlinpython (>=3.4.10)
